jpcli/__init__.py
jpcli/__main__.py
jpcli/main.py
jpcli/parsers/__init__.py
jpcli/parsers/cmdline_parser.py
jpcli/parsers/cpuinfo_parser.py
jpcli/parsers/df_parser.py
jpcli/parsers/dmesg_parser.py
jpcli/parsers/free_parser.py
jpcli/parsers/ifconfig_parser.py
jpcli/parsers/journalctl_parser.py
jpcli/parsers/lsblk_parser.py
jpcli/parsers/lscpu_parser.py
jpcli/parsers/lshw_parser.py
jpcli/parsers/lsmem_parser.py
jpcli/parsers/lsusb_parser.py
jpcli/parsers/mcelog_parser.py
jpcli/parsers/os_release_parser.py
jpcli/parsers/uname_parser.py
tests/__init__.py
tests/test_lsmem_parser.py
tests/test_other_command_parser.py
jpcli-1.0.1.dist-info/LICENCE
jpcli-1.0.1.dist-info/METADATA
jpcli-1.0.1.dist-info/WHEEL
jpcli-1.0.1.dist-info/entry_points.txt
jpcli-1.0.1.dist-info/top_level.txt
jpcli-1.0.1.dist-info/RECORD
